simple_file_org/main.py
simple_file_org-0.1.1.dist-info/METADATA
simple_file_org-0.1.1.dist-info/WHEEL
simple_file_org-0.1.1.dist-info/entry_points.txt
simple_file_org-0.1.1.dist-info/RECORD
