Metadata-Version: 2.3
Name: simple-file-org
Version: 0.1.1
Summary: Organize files into folders based on creation times
Requires-Python: >=3.12
Requires-Dist: pydate>=1.2.0
Requires-Dist: pytz>=2024.1
Requires-Dist: typer>=0.12.3
